README.rst
setup.cfg
setup.py
dato/__init__.py
dato/deploy/__init__.py
dato/deploy/_client.py
dato_predictive_service_client.egg-info/PKG-INFO
dato_predictive_service_client.egg-info/SOURCES.txt
dato_predictive_service_client.egg-info/dependency_links.txt
dato_predictive_service_client.egg-info/requires.txt
dato_predictive_service_client.egg-info/top_level.txt